cmoat/__init__.py
cmoat/__main__.py
cmoat/__version__.py
cmoat/GUI_lib/GUI.py
cmoat/GUI_lib/GUI_init.py
cmoat/GUI_lib/app_init/packages_check.py
cmoat/argument_parser/GUI.py
cmoat/argument_parser/__init__.py
cmoat/argument_parser/batch_analyse.py
cmoat/argument_parser/single_analyse.py
cmoat/libs/cptac_data.py
cmoat/libs/analysis_tasks/analysis_task_base.py
cmoat/libs/analysis_tasks/correlation_curve_task.py
cmoat/libs/analysis_tasks/dual_positive_survival_task.py
cmoat/libs/analysis_tasks/expression_boxplot_task.py
cmoat/libs/analysis_tasks/normal_tissue_api.py
cmoat/libs/analysis_tasks/normal_tissue_task.py
cmoat/libs/analysis_tasks/survival_analysis_task.py
cmoat-0.1.4.dist-info/licenses/LICENSE
cmoat-0.1.4.dist-info/METADATA
cmoat-0.1.4.dist-info/WHEEL
cmoat-0.1.4.dist-info/entry_points.txt
cmoat-0.1.4.dist-info/top_level.txt
cmoat-0.1.4.dist-info/RECORD
